nmk_vscode/__init__.py
nmk_vscode/_version.py
nmk_vscode/builders.py
nmk_vscode/extensions.yml
nmk_vscode/launch.yml
nmk_vscode/plugin.yml
nmk_vscode/settings.yml
nmk_vscode/tasks.yml
nmk_vscode/_buildenv/__init__.py
nmk_vscode/_buildenv/extension.py
nmk_vscode/_buildenv/legacy.py
nmk_vscode/_templates/__init__.py
nmk_vscode/_templates/base_settings.json.jinja
nmk_vscode/_templates/tasks.json.jinja
nmk_vscode/_templates/vscode.sh.jinja
nmk_vscode-1.4.1.dist-info/licenses/LICENSE
nmk_vscode-1.4.1.dist-info/METADATA
nmk_vscode-1.4.1.dist-info/WHEEL
nmk_vscode-1.4.1.dist-info/entry_points.txt
nmk_vscode-1.4.1.dist-info/top_level.txt
nmk_vscode-1.4.1.dist-info/RECORD
